towles_tool/__init__.py
towles_tool/__main__.py
towles_tool/cli.py
towles_tool/config.py
towles_tool-0.0.7.dist-info/METADATA
towles_tool-0.0.7.dist-info/WHEEL
towles_tool-0.0.7.dist-info/entry_points.txt
towles_tool-0.0.7.dist-info/licenses/LICENSE
towles_tool-0.0.7.dist-info/RECORD
