Metadata-Version: 2.4
Name: towles-tool
Version: 0.0.7
Summary: Helper cli commands from a developer
Project-URL: Homepage, https://ChrisTowles.github.io/towles-tool/
Project-URL: Repository, https://github.com/ChrisTowles/towles-tool
Project-URL: Documentation, https://ChrisTowles.github.io/towles-tool/
Author-email: Chris Towles <chris.towles.dev01@gmail.com>
License-File: LICENSE
Keywords: cli,python,towles
Classifier: Intended Audience :: Developers
Classifier: Programming Language :: Python
Classifier: Programming Language :: Python :: 3
Classifier: Programming Language :: Python :: 3.9
Classifier: Programming Language :: Python :: 3.10
Classifier: Programming Language :: Python :: 3.11
Classifier: Programming Language :: Python :: 3.12
Classifier: Programming Language :: Python :: 3.13
Classifier: Topic :: Software Development :: Libraries :: Python Modules
Requires-Python: <4.0,>=3.9
Requires-Dist: platformdirs>=4.3.8
Requires-Dist: pydantic>=2.11.5
Requires-Dist: pyyaml>=6.0.2
Requires-Dist: rich>=14.0.0
Requires-Dist: typer>=0.16.0
